practica/mux2_4.v
module mux2_4(output wire [3:0] Out, input wire [3:0] A, input wire [3:0] B, input wire s);

  assign Out = s == 0 ? A : B; 

endmodule

practica/mux4_1.v
module mux4_1(output reg out, input wire a, b, c, d, input wire [1:0] S);

  always @(a or b or c or d or S) 
  case (S)
    2'b00: out = a;
    2'b01: out = b;
    2'b10: out = c;
    2'b11: out = d;
    
    default: out = 'bx; 
  endcase
  
endmodule

modificacion/cl.v
module cl(output wire out, input wire a, b, input wire [1:0] S);

  wire out_and, out_or, out_xor, out_not;

  and and1(out_and, a, b);
  or or1(out_or, a, b);
  xor xor1(out_xor, a, b);
  not not1(out_not, a);
  
  mux4_1 mux(out, out_and, out_or, out_xor, out_not, S);

endmodule

P01/modificacion/ul4.v
module ul4(output wire[3:0] Out, input wire[3:0] A, input wire[3:0] B, input wire [1:0] S);
  //Hace las operaciones de la celda lógica a todos los bits

  cl cl1 (Out[0], A[0], B[0], S);
  cl cl2 (Out[1], A[1], B[1], S);
  cl cl3 (Out[2], A[2], B[2], S);
  cl cl4 (Out[3], A[3], B[3], S);

  // cl cl0(Out[3:0], A[3:0], B[3:0], S);

endmodule

P01/modificacion/fa.v
module fa(output wire c_out, sum, input wire a, b, c_in);

  assign{c_out, sum} = a + b + c_in; 

endmodule

P01/modificacion/sum4.v
module sum4(output wire[3:0] S, output wire c_out, input wire[3:0] A, input wire[3:0] B, input wire c_in);

  wire out_carry1, out_carry2, out_carry3;

  fa fa_1(out_carry1, S[0], A[0], B[0], c_in);
  fa fa_2(out_carry2, S[1], A[1], B[1], out_carry1);
  fa fa_3(out_carry3, S[2], A[2], B[2], out_carry2);
  fa fa_4(c_out, S[3], A[3], B[3], out_carry3);

endmodule

practica/compl1.v
module compl1 (output wire [3:0] Out, input wire [3:0] Inp, input wire cpl);
  /*
  wire comple1;
  not not1 (comple1, Inp);

  always @(cpl) 
  begin
    if (cpl == 0) begin
      Out = Inp; 
    end
    else begin
      Out = ~Inp;
    end
  end
  */

  //Aqui no podemos hacer modelado de commportamiento porque nuestras variables no son reg

  assign Out = cpl == 1 ? ~Inp : Inp;

endmodule

P01/practica/alu.v
module alu(output wire [3:0] R, output wire zero, c_out, sign, input wire [3:0] A, B, input wire c_in,
input wire [1:0] ALUOP, input wire l);
  
  wire[3:0] out_mux2_4_1, out_OP2, out_add1, out_OP1, out_suma, out_ul4;

  mux2_4 mux_1 (out_mux2_4_1, A, B, op2_B); 
  compl1 complemento_1 (out_OP2, out_mux2_4_1, cpl);
  mux2_4 add_1 (out_add1, 4'b0000, 4'b0001, add1);
  mux2_4 mux_2 (out_OP1, out_add1, A, op1_A);

  sum4 suma_12 (out_suma, c_out, out_OP1, out_OP2, c_in);
  ul4 ul4_12 (out_ul4, out_OP1, out_OP2, ALUOP); 
  
  mux2_4 Final (R, out_suma, out_ul4, l);

  /*
  assign add1 = ~l & ALUOP[0]; 
  assign op1_A = ALUOP[1] & (~ALUOP[0]) | l & ~ALUOP[1];
  assign op2_B = ALUOP[1] & (~ALUOP[0]) | l & ~ALUOP[1];
  assign cpl =   (~l &  ~ALUOP[1] & ALUOP[0]) | (l & ALUOP[1] & ALUOP[0]);
  */  

  assign zero = R == 0 ? 1 : 0;
  assign sign = R[3]; //

  assign add1 = (~l & ALUOP[0]); //not A and c 
  assign op1_A = (ALUOP[1] & ~ALUOP[0]) | (l); // B and not C
  assign op2_B = (ALUOP[1] & ~ALUOP[0]) | (l & ~ALUOP[1]); // B and not C or A and not B
  assign cpl = (~l & ~ALUOP[1] & ALUOP[0]);  // not A and not B and C

endmodule

P01/modificacion/alu_mod_tb.v
// Testbench para modulo alu
`timescale 1 ns / 10 ps //Directiva que fija la unidad de tiempo de simulación y la precision de la unidad
module alu_tb;
//Modificación de reemplazar la operación de incremento de A por complemento a 1 de B
//declaracion de señales
reg [1:0] t_Op;
reg t_l, t_cin;
reg [3:0] t_A, t_B; 
wire [3:0] t_R;
wire t_z, t_c, t_s;
integer errores;

// error de cualquier tipo, de resultado, de linea zero, de signo y carry
reg error, error_R, error_z, error_s, error_c; 

//instancia del modulo a testear
alu mat(t_R, t_z, t_c, t_s, t_A, t_B, t_cin, t_Op, t_l);


initial
begin
	$dumpfile("alu.vcd");
	$dumpvars;

	errores = 0;
	t_l = 1'b0;
	repeat(2)
	begin
		t_Op = 2'b0;
		repeat(4)
		begin
			t_cin = 1'b0;
			repeat(2)
			begin
		    	t_A = 4'b0;
		    	repeat(16) 
		    	begin
					t_B = 4'b0;
					repeat(16) 
			  		begin
						#0.01 check;
						#9.99;
						t_B = t_B + 1;
			  		end
			  		t_A = t_A + 1;
		    	end
				t_cin = t_cin + 1;
			end
			t_Op = t_Op + 1;
		end
		t_l = t_l + 1;
	end
	$display("Encontradas %d operaciones erroneas", errores);
  	//fin simulacion
  	$finish;
end

// Tarea para hacer la comprobación automática de resultados
task check;
reg [4:0] expected_R;
reg expected_z, expected_c, expected_s;

begin
	$write("tiempo=%0d A=%b B=%b c_in=%b L=%b OP=%b R=%b, Z=%b, C=%b, S=%b.", $time, t_A, t_B, t_cin, t_l, t_Op, t_R, t_z, t_c, t_s);

	// Si las operaciones son lógicas
	if (t_l)
	begin
		case (t_Op)
			2'b00: expected_R[3:0] = t_A & t_B;
			2'b01: expected_R[3:0] = t_A | t_B;
			2'b10: expected_R[3:0] = t_A ^ t_B;
			2'b11: expected_R[3:0] = ~t_A;
			default: $display("ERROR. Valor no esperado para t_Op: %b", t_Op);
		endcase
		// Se establece a 0, pero realmente es un "don't care"
		expected_c = 1'b0;
		expected_s = expected_R[3];
		// las operaciones lógicas no pueden tener error de signo o acarreo
		error_s = 0;
	 	error_c = 0;
	end
	else
	begin
		case (t_Op)
			2'b00: expected_R = t_A + t_cin;
			2'b01: expected_R = (t_A ^4'b1111) + 4'b0001 + t_cin;
			2'b10: expected_R = t_A + t_B + t_cin;
			2'b11: expected_R = ~(t_B[3:0]) + t_cin;
			default: $display("ERROR. Valor no esperado para t_Op: %b", t_Op);
		endcase
		expected_c = expected_R[4];
		expected_s = expected_R[3];
		// generacion señales error específicas operaciones aritmeticas
		error_s = (expected_s !== t_s);
		if (t_Op == 2'b11)
			error_c = 0;
		else
	 		error_c = (expected_c !== t_c);
	end

	expected_z = ~| expected_R[3:0];
	// generacion señales error generales para toda la ALU
	error_R = (expected_R[3:0] !== t_R); 
	error_z = (expected_z !== t_z);
	error = error_R | error_z | error_s | error_c;
	if (error)
	begin
		errores = errores + 1;
		$display(" ---- ERROR");
		if (error_R)
			$display("\tResultado esperado %b, obtenido %b", expected_R[3:0], t_R);
		if (error_z)
			$display("\tFlag de cero esperado %b, obtenido %b", expected_z, t_z);
		if (error_s)
			$display("\tFlag de signo esperado %b, obtenido %b", expected_s, t_s);
		if (error_c)
			$display("\tFlag de acarreo esperado %b, obtenido %b", expected_c, t_c);
	end
	else
		$display(" ---- OK");
end
endtask
endmodule

P01/practica/alu.vcd
$date
	Tue Oct 24 15:57:07 2023
$end
$version
	Icarus Verilog
$end
$timescale
	10ps
$end
$scope module alu_tb $end
$var wire 1 ! t_z $end
$var wire 1 " t_s $end
$var wire 1 # t_c $end
$var wire 4 $ t_R [3:0] $end
$var reg 1 % error $end
$var reg 1 & error_R $end
$var reg 1 ' error_c $end
$var reg 1 ( error_s $end
$var reg 1 ) error_z $end
$var reg 4 * t_A [3:0] $end
$var reg 4 + t_B [3:0] $end
$var reg 2 , t_Op [1:0] $end
$var reg 1 - t_cin $end
$var reg 1 . t_l $end
$var integer 32 / errores [31:0] $end
$scope module mat $end
$var wire 4 0 A [3:0] $end
$var wire 2 1 ALUOP [1:0] $end
$var wire 4 2 B [3:0] $end
$var wire 1 3 add1 $end
$var wire 1 - c_in $end
$var wire 1 4 cpl $end
$var wire 1 . l $end
$var wire 1 5 op1_A $end
$var wire 1 6 op2_B $end
$var wire 1 ! zero $end
$var wire 1 " sign $end
$var wire 4 7 out_ul4 [3:0] $end
$var wire 4 8 out_suma [3:0] $end
$var wire 4 9 out_mux2_4_1 [3:0] $end
$var wire 4 : out_add1 [3:0] $end
$var wire 4 ; out_OP2 [3:0] $end
$var wire 4 < out_OP1 [3:0] $end
$var wire 1 # c_out $end
$var wire 4 = R [3:0] $end
$scope module Final $end
$var wire 1 . s $end
$var wire 4 > Out [3:0] $end
$var wire 4 ? B [3:0] $end
$var wire 4 @ A [3:0] $end
$upscope $end
$scope module add_1 $end
$var wire 4 A A [3:0] $end
$var wire 4 B B [3:0] $end
$var wire 1 3 s $end
$var wire 4 C Out [3:0] $end
$upscope $end
$scope module complemento_1 $end
$var wire 1 4 cpl $end
$var wire 4 D Out [3:0] $end
$var wire 4 E Inp [3:0] $end
$upscope $end
$scope module mux_1 $end
$var wire 4 F A [3:0] $end
$var wire 4 G B [3:0] $end
$var wire 1 6 s $end
$var wire 4 H Out [3:0] $end
$upscope $end
$scope module mux_2 $end
$var wire 4 I A [3:0] $end
$var wire 4 J B [3:0] $end
$var wire 1 5 s $end
$var wire 4 K Out [3:0] $end
$upscope $end
$scope module suma_12 $end
$var wire 4 L A [3:0] $end
$var wire 4 M B [3:0] $end
$var wire 1 - c_in $end
$var wire 1 N out_carry3 $end
$var wire 1 O out_carry2 $end
$var wire 1 P out_carry1 $end
$var wire 1 # c_out $end
$var wire 4 Q S [3:0] $end
$scope module fa_1 $end
$var wire 1 R a $end
$var wire 1 S b $end
$var wire 1 - c_in $end
$var wire 1 T sum $end
$var wire 1 P c_out $end
$upscope $end
$scope module fa_2 $end
$var wire 1 U a $end
$var wire 1 V b $end
$var wire 1 P c_in $end
$var wire 1 W sum $end
$var wire 1 O c_out $end
$upscope $end
$scope module fa_3 $end
$var wire 1 X a $end
$var wire 1 Y b $end
$var wire 1 O c_in $end
$var wire 1 Z sum $end
$var wire 1 N c_out $end
$upscope $end
$scope module fa_4 $end
$var wire 1 [ a $end
$var wire 1 \ b $end
$var wire 1 N c_in $end
$var wire 1 ] sum $end
$var wire 1 # c_out $end
$upscope $end
$upscope $end
$scope module ul4_12 $end
$var wire 4 ^ A [3:0] $end
$var wire 4 _ B [3:0] $end
$var wire 2 ` S [1:0] $end
$var wire 4 a Out [3:0] $end
$scope module cl1 $end
$var wire 2 b S [1:0] $end
$var wire 1 c a $end
$var wire 1 d b $end
$var wire 1 e out_and $end
$var wire 1 f out_not $end
$var wire 1 g out_or $end
$var wire 1 h out_xor $end
$var wire 1 i out $end
$scope module mux $end
$var wire 2 j S [1:0] $end
$var wire 1 e a $end
$var wire 1 g b $end
$var wire 1 h c $end
$var wire 1 f d $end
$var reg 1 i out $end
$upscope $end
$upscope $end
$scope module cl2 $end
$var wire 2 k S [1:0] $end
$var wire 1 l a $end
$var wire 1 m b $end
$var wire 1 n out_and $end
$var wire 1 o out_not $end
$var wire 1 p out_or $end
$var wire 1 q out_xor $end
$var wire 1 r out $end
$scope module mux $end
$var wire 2 s S [1:0] $end
$var wire 1 n a $end
$var wire 1 p b $end
$var wire 1 q c $end
$var wire 1 o d $end
$var reg 1 r out $end
$upscope $end
$upscope $end
$scope module cl3 $end
$var wire 2 t S [1:0] $end
$var wire 1 u a $end
$var wire 1 v b $end
$var wire 1 w out_and $end
$var wire 1 x out_not $end
$var wire 1 y out_or $end
$var wire 1 z out_xor $end
$var wire 1 { out $end
$scope module mux $end
$var wire 2 | S [1:0] $end
$var wire 1 w a $end
$var wire 1 y b $end
$var wire 1 z c $end
$var wire 1 x d $end
$var reg 1 { out $end
$upscope $end
$upscope $end
$scope module cl4 $end
$var wire 2 } S [1:0] $end
$var wire 1 ~ a $end
$var wire 1 !" b $end
$var wire 1 "" out_and $end
$var wire 1 #" out_not $end
$var wire 1 $" out_or $end
$var wire 1 %" out_xor $end
$var wire 1 &" out $end
$scope module mux $end
$var wire 2 '" S [1:0] $end
$var wire 1 "" a $end
$var wire 1 $" b $end
$var wire 1 %" c $end
$var wire 1 #" d $end
$var reg 1 &" out $end
$upscope $end
$upscope $end
$upscope $end
$upscope $end
$scope task check $end
$var reg 5 (" expected_R [4:0] $end
$var reg 1 )" expected_c $end
$var reg 1 *" expected_s $end
$var reg 1 +" expected_z $end
$upscope $end
$upscope $end
$enddefinitions $end
#0
$dumpvars
x+"
x*"
x)"
bx ("
b0 '"
0&"
0%"
0$"
1#"
0""
0!"
0~
b0 }
b0 |
0{
0z
0y
1x
0w
0v
0u
b0 t
b0 s
0r
0q
0p
1o
0n
0m
0l
b0 k
b0 j
0i
0h
0g
1f
0e
0d
0c
b0 b
b0 a
b0 `
b0 _
b0 ^
0]
0\
0[
0Z
0Y
0X
0W
0V
0U
0T
0S
0R
b0 Q
0P
0O
0N
b0 M
b0 L
b0 K
b0 J
b0 I
b0 H
b0 G
b0 F
b0 E
b0 D
b0 C
b1 B
b0 A
b0 @
b0 ?
b0 >
b0 =
b0 <
b0 ;
b0 :
b0 9
b0 8
b0 7
06
05
04
03
b0 2
b0 1
b0 0
b0 /
0.
0-
b0 ,
b0 +
b0 *
x)
x(
x'
x&
x%
b0 $
0#
0"
1!
$end
#1
0%
0)
0&
1+"
0'
0(
0*"
0)"
b0 ("
#1000
b1 +
b1 2
b1 G
#2000
b10 +
b10 2
b10 G
#3000
b11 +
b11 2
b11 G
#4000
b100 +
b100 2
b100 G
#5000
b101 +
b101 2
b101 G
#6000
b110 +
b110 2
b110 G
#7000
b111 +
b111 2
b111 G
#8000
b1000 +
b1000 2
b1000 G
#9000
b1001 +
b1001 2
b1001 G
#10000
b1010 +
b1010 2
b1010 G
#11000
b1011 +
b1011 2
b1011 G
#12000
b1100 +
b1100 2
b1100 G
#13000
b1101 +
b1101 2
b1101 G
#14000
b1110 +
b1110 2
b1110 G
#15000
b1111 +
b1111 2
b1111 G
#16000
0!
b1 $
b1 =
b1 >
b1 8
b1 @
b1 Q
1T
1g
1h
1S
1d
b1 ;
b1 D
b1 M
b1 _
b1 9
b1 E
b1 H
b1 *
b1 0
b1 F
b1 J
b0 +
b0 2
b0 G
#16001
0+"
b1 ("
#17000
b1 +
b1 2
b1 G
#18000
b10 +
b10 2
b10 G
#19000
b11 +
b11 2
b11 G
#20000
b100 +
b100 2
b100 G
#21000
b101 +
b101 2
b101 G
#22000
b110 +
b110 2
b110 G
#23000
b111 +
b111 2
b111 G
#24000
b1000 +
b1000 2
b1000 G
#25000
b1001 +
b1001 2
b1001 G
#26000
b1010 +
b1010 2
b1010 G
#27000
b1011 +
b1011 2
b1011 G
#28000
b1100 +
b1100 2
b1100 G
#29000
b1101 +
b1101 2
b1101 G
#30000
b1110 +
b1110 2
b1110 G
#31000
b1111 +
b1111 2
b1111 G
#32000
b10 $
b10 =
b10 >
0T
b10 8
b10 @
b10 Q
1W
0g
0h
1p
1q
0S
1V
0d
1m
b10 ;
b10 D
b10 M
b10 _
b10 9
b10 E
b10 H
b10 *
b10 0
b10 F
b10 J
b0 +
b0 2
b0 G
#32001
b10 ("
#33000
b1 +
b1 2
b1 G
#34000
b10 +
b10 2
b10 G
#35000
b11 +
b11 2
b11 G
#36000
b100 +
b100 2
b100 G
#37000
b101 +
b101 2
b101 G
#38000
b110 +
b110 2
b110 G
#39000
b111 +
b111 2
b111 G
#40000
b1000 +
b1000 2
b1000 G
#41000
b1001 +
b1001 2
b1001 G
#42000
b1010 +
b1010 2
b1010 G
#43000
b1011 +
b1011 2
b1011 G
#44000
b1100 +
b1100 2
b1100 G
#45000
b1101 +
b1101 2
b1101 G
#46000
b1110 +
b1110 2
b1110 G
#47000
b1111 +
b1111 2
b1111 G
#48000
b11 $
b11 =
b11 >
b11 8
b11 @
b11 Q
1T
1g
1h
1S
1d
b11 ;
b11 D
b11 M
b11 _
b11 9
b11 E
b11 H
b11 *
b11 0
b11 F
b11 J
b0 +
b0 2
b0 G
#48001
b11 ("
#49000
b1 +
b1 2
b1 G
#50000
b10 +
b10 2
b10 G
#51000
b11 +
b11 2
b11 G
#52000
b100 +
b100 2
b100 G
#53000
b101 +
b101 2
b101 G
#54000
b110 +
b110 2
b110 G
#55000
b111 +
b111 2
b111 G
#56000
b1000 +
b1000 2
b1000 G
#57000
b1001 +
b1001 2
b1001 G
#58000
b1010 +
b1010 2
b1010 G
#59000
b1011 +
b1011 2
b1011 G
#60000
b1100 +
b1100 2
b1100 G
#61000
b1101 +
b1101 2
b1101 G
#62000
b1110 +
b1110 2
b1110 G
#63000
b1111 +
b1111 2
b1111 G
#64000
b100 $
b100 =
b100 >
0T
0W
b100 8
b100 @
b100 Q
1Z
0g
0h
0p
0q
1y
1z
0S
0V
1Y
0d
0m
1v
b100 ;
b100 D
b100 M
b100 _
b100 9
b100 E
b100 H
b100 *
b100 0
b100 F
b100 J
b0 +
b0 2
b0 G
#64001
b100 ("
#65000
b1 +
b1 2
b1 G
#66000
b10 +
b10 2
b10 G
#67000
b11 +
b11 2
b11 G
#68000
b100 +
b100 2
b100 G
#69000
b101 +
b101 2
b101 G
#70000
b110 +
b110 2
b110 G
#71000
b111 +
b111 2
b111 G
#72000
b1000 +
b1000 2
b1000 G
#73000
b1001 +
b1001 2
b1001 G
#74000
b1010 +
b1010 2
b1010 G
#75000
b1011 +
b1011 2
b1011 G
#76000
b1100 +
b1100 2
b1100 G
#77000
b1101 +
b1101 2
b1101 G
#78000
b1110 +
b1110 2
b1110 G
#79000
b1111 +
b1111 2
b1111 G
#80000
b101 $
b101 =
b101 >
b101 8
b101 @
b101 Q
1T
1g
1h
1S
1d
b101 ;
b101 D
b101 M
b101 _
b101 9
b101 E
b101 H
b101 *
b101 0
b101 F
b101 J
b0 +
b0 2
b0 G
#80001
b101 ("
#81000
b1 +
b1 2
b1 G
#82000
b10 +
b10 2
b10 G
#83000
b11 +
b11 2
b11 G
#84000
b100 +
b100 2
b100 G
#85000
b101 +
b101 2
b101 G
#86000
b110 +
b110 2
b110 G
#87000
b111 +
b111 2
b111 G
#88000
b1000 +
b1000 2
b1000 G
#89000
b1001 +
b1001 2
b1001 G
#90000
b1010 +
b1010 2
b1010 G
#91000
b1011 +
b1011 2
b1011 G
#92000
b1100 +
b1100 2
b1100 G
#93000
b1101 +
b1101 2
b1101 G
#94000
b1110 +
b1110 2
b1110 G
#95000
b1111 +
b1111 2
b1111 G
#96000
b110 $
b110 =
b110 >
0T
b110 8
b110 @
b110 Q
1W
0g
0h
1p
1q
0S
1V
0d
1m
b110 ;
b110 D
b110 M
b110 _
b110 9
b110 E
b110 H
b110 *
b110 0
b110 F
b110 J
b0 +
b0 2
b0 G
#96001
b110 ("
#97000
b1 +
b1 2
b1 G
#98000
b10 +
b10 2
b10 G
#99000
b11 +
b11 2
b11 G
#100000
b100 +
b100 2
b100 G
#101000
b101 +
b101 2
b101 G
#102000
b110 +
b110 2
b110 G
#103000
b111 +
b111 2
b111 G
#104000
b1000 +
b1000 2
b1000 G
#105000
b1001 +
b1001 2
b1001 G
#106000
b1010 +
b1010 2
b1010 G
#107000
b1011 +
b1011 2
b1011 G
#108000
b1100 +
b1100 2
b1100 G
#109000
b1101 +
b1101 2
b1101 G
#110000
b1110 +
b1110 2
b1110 G
#111000
b1111 +
b1111 2
b1111 G
#112000
b111 $
b111 =
b111 >
b111 8
b111 @
b111 Q
1T
1g
1h
1S
1d
b111 ;
b111 D
b111 M
b111 _
b111 9
b111 E
b111 H
b111 *
b111 0
b111 F
b111 J
b0 +
b0 2
b0 G
#112001
b111 ("
#113000
b1 +
b1 2
b1 G
#114000
b10 +
b10 2
b10 G
#115000
b11 +
b11 2
b11 G
#116000
b100 +
b100 2
b100 G
#117000
b101 +
b101 2
b101 G
#118000
b110 +
b110 2
b110 G
#119000
b111 +
b111 2
b111 G
#120000
b1000 +
b1000 2
b1000 G
#121000
b1001 +
b1001 2
b1001 G
#122000
b1010 +
b1010 2
b1010 G
#123000
b1011 +
b1011 2
b1011 G
#124000
b1100 +
b1100 2
b1100 G
#125000
b1101 +
b1101 2
b1101 G
#126000
b1110 +
b1110 2
b1110 G
#127000
b1111 +
b1111 2
b1111 G
#128000
1"
b1000 $
b1000 =
b1000 >
0T
0W
0Z
b1000 8
b1000 @
b1000 Q
1]
0g
0h
0p
0q
0y
0z
1$"
1%"
0S
0V
0Y
1\
0d
0m
0v
1!"
b1000 ;
b1000 D
b1000 M
b1000 _
b1000 9
b1000 E
b1000 H
b1000 *
b1000 0
b1000 F
b1000 J
b0 +
b0 2
b0 G
#128001
1*"
b1000 ("
#129000
b1 +
b1 2
b1 G
#130000
b10 +
b10 2
b10 G
#131000
b11 +
b11 2
b11 G
#132000
b100 +
b100 2
b100 G
#133000
b101 +
b101 2
b101 G
#134000
b110 +
b110 2
b110 G
#135000
b111 +
b111 2
b111 G
#136000
b1000 +
b1000 2
b1000 G
#137000
b1001 +
b1001 2
b1001 G
#138000
b1010 +
b1010 2
b1010 G
#139000
b1011 +
b1011 2
b1011 G
#140000
b1100 +
b1100 2
b1100 G
#141000
b1101 +
b1101 2
b1101 G
#142000
b1110 +
b1110 2
b1110 G
#143000
b1111 +
b1111 2
b1111 G
#144000
b1001 $
b1001 =
b1001 >
b1001 8
b1001 @
b1001 Q
1T
1g
1h
1S
1d
b1001 ;
b1001 D
b1001 M
b1001 _
b1001 9
b1001 E
b1001 H
b1001 *
b1001 0
b1001 F
b1001 J
b0 +
b0 2
b0 G
#144001
b1001 ("
#145000
b1 +
b1 2
b1 G
#146000
b10 +
b10 2
b10 G
#147000
b11 +
b11 2
b11 G
#148000
b100 +
b100 2
b100 G
#149000
b101 +
b101 2
b101 G
#150000
b110 +
b110 2
b110 G
#151000
b111 +
b111 2
b111 G
#152000
b1000 +
b1000 2
b1000 G
#153000
b1001 +
b1001 2
b1001 G
#154000
b1010 +
b1010 2
b1010 G
#155000
b1011 +
b1011 2
b1011 G
#156000
b1100 +
b1100 2
b1100 G
#157000
b1101 +
b1101 2
b1101 G
#158000
b1110 +
b1110 2
b1110 G
#159000
b1111 +
b1111 2
b1111 G
#160000
b1010 $
b1010 =
b1010 >
0T
b1010 8
b1010 @
b1010 Q
1W
0g
0h
1p
1q
0S
1V
0d
1m
b1010 ;
b1010 D
b1010 M
b1010 _
b1010 9
b1010 E
b1010 H
b1010 *
b1010 0
b1010 F
b1010 J
b0 +
b0 2
b0 G
#160001
b1010 ("
#161000
b1 +
b1 2
b1 G
#162000
b10 +
b10 2
b10 G
#163000
b11 +
b11 2
b11 G
#164000
b100 +
b100 2
b100 G
#165000
b101 +
b101 2
b101 G
#166000
b110 +
b110 2
b110 G
#167000
b111 +
b111 2
b111 G
#168000
b1000 +
b1000 2
b1000 G
#169000
b1001 +
b1001 2
b1001 G
#170000
b1010 +
b1010 2
b1010 G
#171000
b1011 +
b1011 2
b1011 G
#172000
b1100 +
b1100 2
b1100 G
#173000
b1101 +
b1101 2
b1101 G
#174000
b1110 +
b1110 2
b1110 G
#175000
b1111 +
b1111 2
b1111 G
#176000
b1011 $
b1011 =
b1011 >
b1011 8
b1011 @
b1011 Q
1T
1g
1h
1S
1d
b1011 ;
b1011 D
b1011 M
b1011 _
b1011 9
b1011 E
b1011 H
b1011 *
b1011 0
b1011 F
b1011 J
b0 +
b0 2
b0 G
#176001
b1011 ("
#177000
b1 +
b1 2
b1 G
#178000
b10 +
b10 2
b10 G
#179000
b11 +
b11 2
b11 G
#180000
b100 +
b100 2
b100 G
#181000
b101 +
b101 2
b101 G
#182000
b110 +
b110 2
b110 G
#183000
b111 +
b111 2
b111 G
#184000
b1000 +
b1000 2
b1000 G
#185000
b1001 +
b1001 2
b1001 G
#186000
b1010 +
b1010 2
b1010 G
#187000
b1011 +
b1011 2
b1011 G
#188000
b1100 +
b1100 2
b1100 G
#189000
b1101 +
b1101 2
b1101 G
#190000
b1110 +
b1110 2
b1110 G
#191000
b1111 +
b1111 2
b1111 G
#192000
b1100 $
b1100 =
b1100 >
0T
0W
b1100 8
b1100 @
b1100 Q
1Z
0g
0h
0p
0q
1y
1z
0S
0V
1Y
0d
0m
1v
b1100 ;
b1100 D
b1100 M
b1100 _
b1100 9
b1100 E
b1100 H
b1100 *
b1100 0
b1100 F
b1100 J
b0 +
b0 2
b0 G
#192001
b1100 ("
#193000
b1 +
b1 2
b1 G
#194000
b10 +
b10 2
b10 G
#195000
b11 +
b11 2
b11 G
#196000
b100 +
b100 2
b100 G
#197000
b101 +
b101 2
b101 G
#198000
b110 +
b110 2
b110 G
#199000
b111 +
b111 2
b111 G
#200000
b1000 +
b1000 2
b1000 G
#201000
b1001 +
b1001 2
b1001 G
#202000
b1010 +
b1010 2
b1010 G
#203000
b1011 +
b1011 2
b1011 G
#204000
b1100 +
b1100 2
b1100 G
#205000
b1101 +
b1101 2
b1101 G
#206000
b1110 +
b1110 2
b1110 G
#207000
b1111 +
b1111 2
b1111 G
#208000
b1101 $
b1101 =
b1101 >
b1101 8
b1101 @
b1101 Q
1T
1g
1h
1S
1d
b1101 ;
b1101 D
b1101 M
b1101 _
b1101 9
b1101 E
b1101 H
b1101 *
b1101 0
b1101 F
b1101 J
b0 +
b0 2
b0 G
#208001
b1101 ("
#209000
b1 +
b1 2
b1 G
#210000
b10 +
b10 2
b10 G
#211000
b11 +
b11 2
b11 G
#212000
b100 +
b100 2
b100 G
#213000
b101 +
b101 2
b101 G
#214000
b110 +
b110 2
b110 G
#215000
b111 +
b111 2
b111 G
#216000
b1000 +
b1000 2
b1000 G
#217000
b1001 +
b1001 2
b1001 G
#218000
b1010 +
b1010 2
b1010 G
#219000
b1011 +
b1011 2
b1011 G
#220000
b1100 +
b1100 2
b1100 G
#221000
b1101 +
b1101 2
b1101 G
#222000
b1110 +
b1110 2
b1110 G
#223000
b1111 +
b1111 2
b1111 G
#224000
b1110 $
b1110 =
b1110 >
0T
b1110 8
b1110 @
b1110 Q
1W
0g
0h
1p
1q
0S
1V
0d
1m
b1110 ;
b1110 D
b1110 M
b1110 _
b1110 9
b1110 E
b1110 H
b1110 *
b1110 0
b1110 F
b1110 J
b0 +
b0 2
b0 G
#224001
b1110 ("
#225000
b1 +
b1 2
b1 G
#226000
b10 +
b10 2
b10 G
#227000
b11 +
b11 2
b11 G
#228000
b100 +
b100 2
b100 G
#229000
b101 +
b101 2
b101 G
#230000
b110 +
b110 2
b110 G
#231000
b111 +
b111 2
b111 G
#232000
b1000 +
b1000 2
b1000 G
#233000
b1001 +
b1001 2
b1001 G
#234000
b1010 +
b1010 2
b1010 G
#235000
b1011 +
b1011 2
b1011 G
#236000
b1100 +
b1100 2
b1100 G
#237000
b1101 +
b1101 2
b1101 G
#238000
b1110 +
b1110 2
b1110 G
#239000
b1111 +
b1111 2
b1111 G
#240000
b1111 $
b1111 =
b1111 >
b1111 8
b1111 @
b1111 Q
1T
1g
1h
1S
1d
b1111 ;
b1111 D
b1111 M
b1111 _
b1111 9
b1111 E
b1111 H
b1111 *
b1111 0
b1111 F
b1111 J
b0 +
b0 2
b0 G
#240001
b1111 ("
#241000
b1 +
b1 2
b1 G
#242000
b10 +
b10 2
b10 G
#243000
b11 +
b11 2
b11 G
#244000
b100 +
b100 2
b100 G
#245000
b101 +
b101 2
b101 G
#246000
b110 +
b110 2
b110 G
#247000
b111 +
b111 2
b111 G
#248000
b1000 +
b1000 2
b1000 G
#249000
b1001 +
b1001 2
b1001 G
#250000
b1010 +
b1010 2
b1010 G
#251000
b1011 +
b1011 2
b1011 G
#252000
b1100 +
b1100 2
b1100 G
#253000
b1101 +
b1101 2
b1101 G
#254000
b1110 +
b1110 2
b1110 G
#255000
b1111 +
b1111 2
b1111 G
#256000
0"
0Z
0]
0g
0h
0p
0q
0y
0z
0$"
0%"
0S
0V
0Y
0\
0d
0m
0v
0!"
b1 $
b1 =
b1 >
0W
0O
b0 ;
b0 D
b0 M
b0 _
b1 8
b1 @
b1 Q
1T
0P
b0 9
b0 E
b0 H
1-
b0 *
b0 0
b0 F
b0 J
b0 +
b0 2
b0 G
#256001
0*"
b1 ("
#257000
b1 +
b1 2
b1 G
#258000
b10 +
b10 2
b10 G
#259000
b11 +
b11 2
b11 G
#260000
b100 +
b100 2
b100 G
#261000
b101 +
b101 2
b101 G
#262000
b110 +
b110 2
b110 G
#263000
b111 +
b111 2
b111 G
#264000
b1000 +
b1000 2
b1000 G
#265000
b1001 +
b1001 2
b1001 G
#266000
b1010 +
b1010 2
b1010 G
#267000
b1011 +
b1011 2
b1011 G
#268000
b1100 +
b1100 2
b1100 G
#269000
b1101 +
b1101 2
b1101 G
#270000
b1110 +
b1110 2
b1110 G
#271000
b1111 +
b1111 2
b1111 G
#272000
b10 $
b10 =
b10 >
1W
b10 8
b10 @
b10 Q
0T
1P
1g
1h
1S
1d
b1 ;
b1 D
b1 M
b1 _
b1 9
b1 E
b1 H
b1 *
b1 0
b1 F
b1 J
b0 +
b0 2
b0 G
#272001
b10 ("
#273000
b1 +
b1 2
b1 G
#274000
b10 +
b10 2
b10 G
#275000
b11 +
b11 2
b11 G
#276000
b100 +
b100 2
b100 G
#277000
b101 +
b101 2
b101 G
#278000
b110 +
b110 2
b110 G
#279000
b111 +
b111 2
b111 G
#280000
b1000 +
b1000 2
b1000 G
#281000
b1001 +
b1001 2
b1001 G
#282000
b1010 +
b1010 2
b1010 G
#283000
b1011 +
b1011 2
b1011 G
#284000
b1100 +
b1100 2
b1100 G
#285000
b1101 +
b1101 2
b1101 G
#286000
b1110 +
b1110 2
b1110 G
#287000
b1111 +
b1111 2
b1111 G
#288000
b11 $
b11 =
b11 >
0Z
1T
0P
b11 8
b11 @
b11 Q
1W
0O
0g
0h
1p
1q
0S
1V
0d
1m
b10 ;
b10 D
b10 M
b10 _
b10 9
b10 E
b10 H
b10 *
b10 0
b10 F
b10 J
b0 +
b0 2
b0 G
#288001
b11 ("
#289000
b1 +
b1 2
b1 G
